{
  "assets": {
    "STH_Maxzzzie": {
      "enabled": true,
      "restartOnChange": true
    },
    "fivem-ipl-master": {
      "enabled": true,
      "restartOnChange": true
    },
    "vSync": {
      "enabled": true,
      "restartOnChange": true
    },
    "MaxSTH": {
      "enabled": true,
      "restartOnChange": true
    },
    "vMenu-master": {
      "enabled": true,
      "restartOnChange": true
    },
    "vMenu": {
      "enabled": false,
      "restartOnChange": false
    },
    "STHmap.fxworld": {
      "enabled": true
    },
    "visual assets": {
      "enabled": true
    },
    "assets": {
      "enabled": true,
      "restartOnChange": true
    },
    "pma-voice": {
      "enabled": true,
      "restartOnChange": true
    }
  },
  "serverUpdateChannel": "latest",
  "systemResources": [
    "baseevents",
    "mapmanager",
    "sessionmanager",
    "yarn",
    "webpack",
    "chat",
    "basic-gamemode",
    "spawnmanager",
    "chat-theme-gtao",
    "playernames",
    "player-data"
  ],
  "name": "SurviveTheHunt_Maxzzzie",
  "createdAt": "2022-04-10T18:54:10.443Z",
  "variables": {
    "voice_useSendingRangeOnly": {
      "setter": "setr",
      "value": false
    },
    "voice_use2dAudio": {
      "setter": "setr",
      "value": false
    },
    "voice_defaultRadio": {
      "setter": "setr",
      "value": "m"
    }
  }
}